YuanmengXiangmuBijiWangzhuanJuejinShicaoXiangmuDianzishu190530/README.md
YuanmengXiangmuBijiWangzhuanJuejinShicaoXiangmuDianzishu190530/__init__.py
YuanmengXiangmuBijiWangzhuanJuejinShicaoXiangmuDianzishu190530/__main__.py
YuanmengXiangmuBijiWangzhuanJuejinShicaoXiangmuDianzishu190530/file.pdf
YuanmengXiangmuBijiWangzhuanJuejinShicaoXiangmuDianzishu190530/index.html
yuanmeng_xiangmu_biji_wangzhuan_juejin_shicao_xiangmu_dianzishu_190530-2024.3.5.0.dist-info/METADATA
yuanmeng_xiangmu_biji_wangzhuan_juejin_shicao_xiangmu_dianzishu_190530-2024.3.5.0.dist-info/WHEEL
yuanmeng_xiangmu_biji_wangzhuan_juejin_shicao_xiangmu_dianzishu_190530-2024.3.5.0.dist-info/entry_points.txt
yuanmeng_xiangmu_biji_wangzhuan_juejin_shicao_xiangmu_dianzishu_190530-2024.3.5.0.dist-info/top_level.txt
yuanmeng_xiangmu_biji_wangzhuan_juejin_shicao_xiangmu_dianzishu_190530-2024.3.5.0.dist-info/RECORD
